acace_utils/__init__.py
acace_utils-0.1.0.dist-info/METADATA
acace_utils-0.1.0.dist-info/WHEEL
acace_utils-0.1.0.dist-info/RECORD
